{
  "id": "BDI001004",
  "level": 2,
  "level_name": {
    "local": "Commune",
    "en": "Commune"
  },
  "name": {
    "local": "Musigati",
    "en": "Musigati",
    "slug": "musigati-bdi001004"
  },
  "code": {
    "id": "BDI001004",
    "iso": null
  },
  "parent": {
    "id": "BDI001",
    "level": 1,
    "name": {
      "local": "Bubanza",
      "en": "Bubanza",
      "slug": "bubanza-bdi001"
    }
  },
  "ancestors": [
    {
      "id": "BDI001",
      "level": 1,
      "name": {
        "local": "Bubanza",
        "en": "Bubanza",
        "slug": "bubanza-bdi001"
      }
    }
  ],
  "children_count": {
    "colline": 23
  },
  "zip_codes": [],
  "geo": {
    "lat": "-3.037",
    "lon": "29.487"
  },
  "metadata": {},
  "source": {}
}